noahs_simple_sentiment_classifier/__init__.py
noahs_simple_sentiment_classifier/textblob_classifier.py
noahs_simple_sentiment_classifier-0.1.1.dist-info/METADATA
noahs_simple_sentiment_classifier-0.1.1.dist-info/WHEEL
noahs_simple_sentiment_classifier-0.1.1.dist-info/top_level.txt
noahs_simple_sentiment_classifier-0.1.1.dist-info/RECORD
